{"cameraMode":{"drawMode":0,"name":"Shaded","section":"Shading Mode"},"sceneLighting":true,"audioPlay":false,"sceneViewState":{"m_AlwaysRefresh":false,"showFog":true,"showSkybox":true,"showFlares":true,"showImageEffects":true,"showParticleSystems":true,"showVisualEffectGraphs":true,"m_FxEnabled":true},"in2DMode":false,"pivot":{"x":2.877725839614868,"y":1.270796537399292,"z":-1.098104476928711},"rotation":{"x":0.05388034135103226,"y":-0.9378156065940857,"z":0.1695021092891693,"w":0.2981277108192444},"size":3.5142014026641847,"orthographic":false}